xlsx_mcp_server/__init__.py
xlsx_mcp_server-0.1.1.dist-info/METADATA
xlsx_mcp_server-0.1.1.dist-info/WHEEL
xlsx_mcp_server-0.1.1.dist-info/entry_points.txt
xlsx_mcp_server-0.1.1.dist-info/RECORD
