Metadata-Version: 2.4
Name: xlsx-mcp-server
Version: 0.1.1
Summary: 一个基于 FastMCP 和 Openpyxl 实现的 Excel MCP 服务器，提供了一系列操作 Excel 文件的工具，可以被 LLM 应用程序调用。
Author-email: bona shen <cn.tony@outlook.com>
Maintainer-email: bona shen <cn.tony@outlook.com>
License-Expression: MIT AND (Apache-2.0 OR BSD-2-Clause)
Keywords: excel,mcp,server
Classifier: License :: OSI Approved :: Apache Software License
Classifier: License :: OSI Approved :: BSD License
Classifier: License :: OSI Approved :: MIT License
Classifier: Programming Language :: Python :: 3
Classifier: Programming Language :: Python :: 3.10
Classifier: Topic :: Software Development :: Libraries :: Python Modules
Requires-Python: >=3.10
Requires-Dist: fastmcp
Requires-Dist: openpyxl
